pyvsnr/__init__.py
pyvsnr/install_cupy.py
pyvsnr/utils.py
pyvsnr/vsnr2d.cu
pyvsnr/vsnr2d.py
pyvsnr/vsnr2d_cuda.py
pyvsnr/precompiled/compile_cuda.sh
pyvsnr/precompiled/libvsnr2d.dll
pyvsnr/precompiled/libvsnr2d.so
pyvsnr-2.3.2.dist-info/METADATA
pyvsnr-2.3.2.dist-info/WHEEL
pyvsnr-2.3.2.dist-info/licenses/LICENSE
pyvsnr-2.3.2.dist-info/RECORD
