Metadata-Version: 2.4
Name: pyvsnr
Version: 2.3.2
Summary: VSNR (Variational Stationary Noise Remover) algorithm in python
Project-URL: repository, https://github.com/CEA-MetroCarac/pyvsnr
Author-email: Killian Pavy <killian.pavy@cea.fr>, Patrick Quemere <patrick.quemere@cea.fr>
License:                     GNU AFFERO GENERAL PUBLIC LICENSE
License-File: LICENSE
Classifier: License :: OSI Approved :: GNU Affero General Public License v3
Classifier: Operating System :: OS Independent
Requires-Python: >=3.9
Requires-Dist: numpy
Requires-Dist: pyfftw
Provides-Extra: test
Requires-Dist: pytest; extra == 'test'
